hfcocoapi/__init__.py
hfcocoapi/const.py
hfcocoapi/models/__init__.py
hfcocoapi/models/category.py
hfcocoapi/models/image.py
hfcocoapi/models/info.py
hfcocoapi/models/license.py
hfcocoapi/processors/__init__.py
hfcocoapi/processors/caption.py
hfcocoapi/processors/instances.py
hfcocoapi/processors/person_keypoint.py
hfcocoapi/processors/processor.py
hfcocoapi/tasks/__init__.py
hfcocoapi/tasks/annotation.py
hfcocoapi/tasks/caption.py
hfcocoapi/tasks/instance.py
hfcocoapi/tasks/person_keypoint.py
hfcocoapi/typehint.py
hfcocoapi/utils.py
huggingface_datasets_cocoapi_tools-0.5.0.dist-info/METADATA
huggingface_datasets_cocoapi_tools-0.5.0.dist-info/WHEEL
huggingface_datasets_cocoapi_tools-0.5.0.dist-info/RECORD
