Metadata-Version: 2.3
Name: huggingface-datasets-cocoapi-tools
Version: 0.5.0
Summary: A helper library for easily converting MSCOCO format data using the loading script of huggingface datasets.
Author: Shunsuke KITADA
Author-email: shunsuke.kitada.0831@gmail.com
Requires-Python: >=3.9,<4.0
Classifier: Programming Language :: Python :: 3
Classifier: Programming Language :: Python :: 3.9
Classifier: Programming Language :: Python :: 3.10
Classifier: Programming Language :: Python :: 3.11
Classifier: Programming Language :: Python :: 3.12
Classifier: Programming Language :: Python :: 3.13
Provides-Extra: all
Provides-Extra: cocoapi
Provides-Extra: datasets
Requires-Dist: datasets[vision] (>=1.0.0) ; extra == "datasets" or extra == "all"
Requires-Dist: pycocotools (>=2.0.2) ; extra == "cocoapi" or extra == "all"
Requires-Dist: pydantic (>=2.0.0)
